{
  "id": "edu_zh_justice_77377d342361",
  "dataset": "education",
  "topic": "justice",
  "language": "zh",
  "platform": "web",
  "source_url": "https://www.163.com/dy/article/KVD4Q7SF055358JA.html",
  "title": "以公正司法维护社会公平正义|法治|法律|司法 ... - 网易",
  "content": "党的十八大以来，围绕保障和促进社会公平正义，我国深入推进司法体制及综合配套改革，社会公平正义保障更为坚实。全面准确落实司法责任制，推行立案登记制，设立巡回法庭，建立检察公益诉讼制度，加强人权司法保障和产权司法保护，依法纠正张氏叔侄案、聂树斌案等重大刑事冤错案件 ...",
  "word_count": 2,
  "crawled_at": "2026-06-17T12:47:00.394305+00:00",
  "content_hash": "77377d342361"
}