{
  "id": "edu_de_success_9dc47f25ef1f",
  "dataset": "education",
  "topic": "success",
  "language": "de",
  "platform": "web",
  "source_url": "https://www.nadinekoehler.de/erfolg/",
  "title": "Was bedeutet Erfolg? Definition von Erfolg | Nadine Koehler",
  "content": "Was bedeutetErfolg? Im Goal Getter LIFE Podcast gehe ich regelmäßig der Frage nach, was es braucht, um erfolgreich zu sein - und wasErfolgeigentlich bedeutet.Erfolgist ein vielschichtiger Begriff, der je nach Kontext, Perspektive und individuellen Wertvorstellungen unterschiedlich interpretiert werden kann. Im Allgemeinen bezieht sichErfolgauf das Erreichen von Zielen, das […]",
  "word_count": 49,
  "crawled_at": "2026-06-17T12:49:04.001165+00:00",
  "content_hash": "9dc47f25ef1f"
}