{
  "id": "edu_en_success_a81e97f94591",
  "dataset": "education",
  "topic": "success",
  "language": "en",
  "platform": "web",
  "source_url": "https://psychcentral.com/blog/does-success-lead-to-happiness",
  "title": "Success and Happiness: Which is Most Important? - Psych Central",
  "content": "Whilesuccesscan lead tohappiness, striving forsuccesscan also lead to stress and unhelpful thoughts. But pursuinghappinessfirst is the key tosuccess.",
  "word_count": 18,
  "crawled_at": "2026-06-17T12:48:25.075909+00:00",
  "content_hash": "a81e97f94591"
}