{
  "id": "edu_de_democracy_df7c83cc15ad",
  "dataset": "education",
  "topic": "democracy",
  "language": "de",
  "platform": "web",
  "source_url": "https://demokratielupe.org/",
  "title": "Demokratielupe - Grundlagen demokratischer Systeme",
  "content": "Für eine vertiefte Auseinandersetzung mit zentralen Aspekten der demokratischen Ordnung enthält diese Website eigenständige Grundlagenbereiche, die unterschiedliche Funktionen im politischenSystemerläutern und systematisch miteinander verknüpft sind.",
  "word_count": 25,
  "crawled_at": "2026-06-17T12:27:53.139287+00:00",
  "content_hash": "df7c83cc15ad"
}