{
  "id": "edu_zh_freedom_9ba7c7ec750b",
  "dataset": "education",
  "topic": "freedom",
  "language": "zh",
  "platform": "web",
  "source_url": "https://www.docin.com/p-4811599295.html",
  "title": "政治哲学中的自由概念-深度研究 - 豆丁网",
  "content": "政治哲学中的自由概念 第一部分 自由概念的起源与发展 2 第二部分 自由的内在含义解析 5 第三部分 政治自由与个人自由区分 8 第四部分 自由主义哲学的主要理论 12 第五部分 自由与平等关系探讨 16 第六部分 自由与秩序之间的张力 20 第七部分 自由限制的正当性分析 24 第八部分 自由价值在当代的 ...",
  "word_count": 25,
  "crawled_at": "2026-06-17T12:45:59.638110+00:00",
  "content_hash": "9ba7c7ec750b"
}