{
  "id": "edu_zh_freedom_0dff02b5dd08",
  "dataset": "education",
  "topic": "freedom",
  "language": "zh",
  "platform": "web",
  "source_url": "https://zh.wikipedia.org/zh-hans/%E8%87%AA%E7%94%B1",
  "title": "自由 - 维基百科，自由的百科全书 - zh.wikipedia.org",
  "content": "自由有多种含义，从不同的角度会有不同的看法，是一个复杂的概念，需要不断地思考和探索 [1]： 法律上意指由 宪法 或 基本法 所保障的一种权利或自由权，包括政府在内任何人都不可以用莫须有的罪名而拘捕扣留任何人。（人身自由） [2] 言论上尽可能地以法律保障与根据其影响力赋以相对应之 ...",
  "word_count": 10,
  "crawled_at": "2026-06-17T12:24:31.271144+00:00",
  "content_hash": "0dff02b5dd08"
}