{
  "source_textbook": {
    "name": "人教版小学数学二年级上册",
    "language": "zh",
    "chapter": "全册",
    "section": "第1-6单元",
    "license": "CC-BY-SA (教育用途)"
  },
  "extracted_concepts": [
    {
      "name": "厘米",
      "aliases": [
        "centimeter",
        "Zentimeter"
      ],
      "definition_snippet": "长度单位，1米=100厘米",
      "category": "concept"
    },
    {
      "name": "米",
      "aliases": [
        "meter",
        "Meter"
      ],
      "definition_snippet": "长度单位，量较长物体用米",
      "category": "concept"
    },
    {
      "name": "乘法",
      "aliases": [
        "multiplication",
        "Multiplikation"
      ],
      "definition_snippet": "求几个相同加数的和的简便运算",
      "category": "operation"
    },
    {
      "name": "乘法口诀",
      "aliases": [
        "multiplication table",
        "Einmaleins"
      ],
      "definition_snippet": "九九乘法表，如一一得一、一二得二",
      "category": "concept"
    },
    {
      "name": "除法",
      "aliases": [
        "division",
        "Division"
      ],
      "definition_snippet": "已知积和一个因数求另一个因数",
      "category": "operation"
    },
    {
      "name": "角",
      "aliases": [
        "angle",
        "Winkel"
      ],
      "definition_snippet": "从一点引出两条射线所组成的图形",
      "category": "concept"
    },
    {
      "name": "直角",
      "aliases": [
        "right angle",
        "rechter Winkel"
      ],
      "definition_snippet": "等于90度的角",
      "category": "concept"
    },
    {
      "name": "锐角",
      "aliases": [
        "acute angle",
        "spitzer Winkel"
      ],
      "definition_snippet": "小于90度的角",
      "category": "concept"
    },
    {
      "name": "钝角",
      "aliases": [
        "obtuse angle",
        "stumpfer Winkel"
      ],
      "definition_snippet": "大于90度且小于180度的角",
      "category": "concept"
    }
  ],
  "extracted_relations": [
    {
      "source": "乘法",
      "target": "加法",
      "type": "generalization",
      "importance": 0.9,
      "evidence": "乘法是相同加数连加的简便运算"
    },
    {
      "source": "除法",
      "target": "乘法",
      "type": "inverse_of",
      "importance": 0.9,
      "evidence": "除法是乘法的逆运算"
    },
    {
      "source": "除法",
      "target": "减法",
      "type": "analogy",
      "importance": 0.7,
      "evidence": "除法之于乘法如同减法之于加法"
    },
    {
      "source": "直角",
      "target": "角",
      "type": "specialization",
      "importance": 0.85,
      "evidence": "直角是90度的特殊角"
    },
    {
      "source": "锐角",
      "target": "角",
      "type": "specialization",
      "importance": 0.8,
      "evidence": "锐角是小于90度的角"
    },
    {
      "source": "钝角",
      "target": "角",
      "type": "specialization",
      "importance": 0.8,
      "evidence": "钝角是大于90度的角"
    },
    {
      "source": "厘米",
      "target": "米",
      "type": "representation",
      "importance": 0.85,
      "evidence": "1米=100厘米"
    },
    {
      "source": "克",
      "target": "千克",
      "type": "representation",
      "importance": 0.85,
      "evidence": "1千克=1000克"
    },
    {
      "source": "直角",
      "target": "角",
      "type": "specialization",
      "importance": 0.9,
      "evidence": "直角是90度的特殊角"
    },
    {
      "source": "锐角",
      "target": "角",
      "type": "specialization",
      "importance": 0.85,
      "evidence": "锐角是小于90度的角"
    },
    {
      "source": "钝角",
      "target": "角",
      "type": "specialization",
      "importance": 0.85,
      "evidence": "钝角是大于90度的角"
    },
    {
      "source": "长方形",
      "target": "正方形",
      "type": "generalization",
      "importance": 0.85,
      "evidence": "正方形是特殊的长方形"
    },
    {
      "source": "正方体",
      "target": "长方体",
      "type": "specialization",
      "importance": 0.85,
      "evidence": "正方体是特殊的长方体"
    },
    {
      "source": "乘法口诀",
      "target": "乘法",
      "type": "representation",
      "importance": 0.9,
      "evidence": "乘法口诀是乘法的速算工具"
    },
    {
      "source": "人民币",
      "target": "小数",
      "type": "requires",
      "importance": 0.8,
      "evidence": "人民币计算涉及小数"
    }
  ]
}